[
  {
    "id": "egkj",
    "preop": "orig",
    "shapes": [
      {
        "type": "circle",
        "geom": {
          "cx": -59.6041259765625,
          "cy": -162.29969787597656,
          "r": 4.769968447263804
        },
        "color": {
          "fill": "#1e88ff",
          "opacity": 0.35
        },
        "outlined": false
      },
      {
        "type": "circle",
        "geom": {
          "cx": -35.490664901733396,
          "cy": -162.48896545410156,
          "r": 4.769968447263804
        },
        "color": {
          "fill": "#1e88ff",
          "opacity": 0.35
        },
        "outlined": false
      },
      {
        "type": "circle",
        "geom": {
          "cx": 35.04609786987305,
          "cy": -162.63982666015625,
          "r": 4.769968447263804
        },
        "color": {
          "fill": "#1e88ff",
          "opacity": 0.35
        },
        "outlined": false
      },
      {
        "type": "circle",
        "geom": {
          "cx": 59.60295455932617,
          "cy": -162.44689208984374,
          "r": 4.769968447263804
        },
        "color": {
          "fill": "#1e88ff",
          "opacity": 0.35
        },
        "outlined": false
      },
      {
        "type": "arrow",
        "geom": {
          "x1": -0.4935106635093689,
          "y1": -34.210174560546875,
          "x2": -0.4935106635093689,
          "y2": -70.42654418945312
        },
        "color": {
          "fill": "#1e88ff",
          "opacity": 0.35
        },
        "outlined": false
      },
      {
        "type": "arrow",
        "geom": {
          "x1": -42.39087677001953,
          "y1": 91.12686157226562,
          "x2": -79.67243194580078,
          "y2": 66.62755584716797
        },
        "color": {
          "fill": "#1e88ff",
          "opacity": 0.35
        },
        "outlined": false
      },
      {
        "type": "arrow",
        "geom": {
          "x1": 44.59941577911377,
          "y1": 91.6863021850586,
          "x2": 79.39553368091583,
          "y2": 68.9623031616211
        },
        "color": {
          "fill": "#1e88ff",
          "opacity": 0.35
        },
        "outlined": false
      },
      {
        "type": "polygon",
        "geom": {
          "points": [
            [
              -20.376370668411255,
              -28.497093200683594
            ],
            [
              -20.329619646072388,
              -4.059455394744873
            ],
            [
              -19.547797441482544,
              -3.5708160400390625
            ],
            [
              -12.07161831855774,
              -3.668544292449951
            ],
            [
              -11.289795160293579,
              -4.40150260925293
            ],
            [
              -11.436387300491333,
              -6.551515579223633
            ],
            [
              10.60123896598816,
              -6.60037899017334
            ],
            [
              10.650103330612183,
              -4.303774833679199
            ],
            [
              11.38306212425232,
              -3.5708160400390625
            ],
            [
              18.761513471603394,
              -3.619680404663086
            ],
            [
              19.7387912273407,
              -4.352639198303223
            ],
            [
              19.595289945602417,
              -28.209285736083984
            ],
            [
              18.752386808395386,
              -28.658832550048828
            ],
            [
              -19.403002977371216,
              -28.658832550048828
            ]
          ]
        },
        "color": {
          "fill": "#1e88ff",
          "opacity": 0.35
        },
        "outlined": false
      },
      {
        "type": "polygon",
        "geom": {
          "points": [
            [
              -98.34758758544922,
              -4.044548988342285
            ],
            [
              -99.82830810546875,
              -5.804649353027344
            ],
            [
              -98.68002319335938,
              131.1140842437744
            ],
            [
              -97.27518463134766,
              132.85608863830566
            ]
          ]
        },
        "color": {
          "fill": "#1e88ff",
          "opacity": 0.65
        },
        "outlined": false
      },
      {
        "type": "polygon",
        "geom": {
          "points": [
            [
              98.39591979980469,
              -4.39417028427124
            ],
            [
              99.77365112304688,
              -6.15766716003418
            ],
            [
              98.76319122314453,
              130.69942092895508
            ],
            [
              97.30216217041016,
              132.32902908325195
            ]
          ]
        },
        "color": {
          "fill": "#1e88ff",
          "opacity": 0.65
        },
        "outlined": false
      }
    ],
    "viewBox": null
  }
]