[
  {
    "id": "nrvk",
    "preop": "orig",
    "shapes": [
      {
        "type": "polygon",
        "geom": {
          "points": [
            [
              -69.78943634033203,
              -165.43716430664062
            ],
            [
              -70.32321166992188,
              -164.86895751953125
            ],
            [
              -70.58148956298828,
              -164.2490997314453
            ],
            [
              -70.61592102050781,
              -163.57757568359375
            ],
            [
              -70.3404312133789,
              -162.768310546875
            ],
            [
              -69.75499725341797,
              -162.1312255859375
            ],
            [
              -68.94573211669922,
              -161.78684997558594
            ],
            [
              -67.92984008789062,
              -161.8212890625
            ],
            [
              -67.29276275634766,
              -162.23452758789062
            ],
            [
              -66.38018035888672,
              -163.19876098632812
            ],
            [
              -65.24375915527344,
              -164.1974334716797
            ],
            [
              -63.986812591552734,
              -165.11001586914062
            ],
            [
              -62.28218460083008,
              -165.95372009277344
            ],
            [
              -60.560340881347656,
              -166.28086853027344
            ],
            [
              -58.56770706176758,
              -166.12368774414062
            ],
            [
              -56.580101013183594,
              -165.25035095214844
            ],
            [
              -54.32146072387695,
              -163.68435668945312
            ],
            [
              -51.867183685302734,
              -166.82400512695312
            ],
            [
              -54.4984245300293,
              -168.7163543701172
            ],
            [
              -56.36568069458008,
              -169.55889892578125
            ],
            [
              -58.55173873901367,
              -170.17372131347656
            ],
            [
              -60.85165023803711,
              -170.28758239746094
            ],
            [
              -63.26542282104492,
              -169.78660583496094
            ],
            [
              -65.13267517089844,
              -169.0806884765625
            ],
            [
              -67.13656616210938,
              -167.82826232910156
            ],
            [
              -68.68502044677734,
              -166.55307006835938
            ]
          ]
        },
        "color": {
          "fill": "#1e88ff",
          "opacity": 0.65
        },
        "outlined": false
      },
      {
        "type": "polygon",
        "geom": {
          "points": [
            [
              -51.86250686645508,
              -166.8082275390625
            ],
            [
              -49.90439224243164,
              -164.96974182128906
            ],
            [
              -48.21183776855469,
              -163.09490966796875
            ],
            [
              -46.59740447998047,
              -161.03781127929688
            ],
            [
              -44.7176399230957,
              -158.4301300048828
            ],
            [
              -42.097618103027344,
              -154.1838836669922
            ],
            [
              -39.41736602783203,
              -149.36544799804688
            ],
            [
              -33.32209014892578,
              -136.9313201904297
            ],
            [
              -27.3941707611084,
              -123.633544921875
            ],
            [
              -19.063037872314453,
              -104.72828674316406
            ],
            [
              -11.07817554473877,
              -87.63078308105469
            ],
            [
              -3.792574882507324,
              -72.91947174072266
            ],
            [
              4.053456783294678,
              -55.54611587524414
            ],
            [
              8.396796226501465,
              -44.61771774291992
            ],
            [
              11.61927318572998,
              -33.96952819824219
            ],
            [
              7.702784538269043,
              -33.19890594482422
            ],
            [
              3.9408514499664307,
              -45.4013786315918
            ],
            [
              -3.348888635635376,
              -62.544281005859375
            ],
            [
              -13.442375183105469,
              -83.69253540039062
            ],
            [
              -26.080228805541992,
              -110.54519653320312
            ],
            [
              -34.29990768432617,
              -129.213623046875
            ],
            [
              -39.85538101196289,
              -141.53082275390625
            ],
            [
              -45.06460952758789,
              -151.28297424316406
            ],
            [
              -49.849830627441406,
              -158.79396057128906
            ],
            [
              -51.99300003051758,
              -161.3669891357422
            ],
            [
              -54.32928466796875,
              -163.66836547851562
            ]
          ]
        },
        "color": {
          "fill": "#1e88ff",
          "opacity": 0.65
        },
        "outlined": false
      },
      {
        "type": "polygon",
        "geom": {
          "points": [
            [
              7.676876068115234,
              -33.18989181518555
            ],
            [
              11.617321014404297,
              -33.96213912963867
            ],
            [
              12.62130355834961,
              -29.148021697998047
            ],
            [
              13.100425720214844,
              -25.24017906188965
            ],
            [
              13.306416511535645,
              -20.70766830444336
            ],
            [
              13.01835823059082,
              -17.04146957397461
            ],
            [
              12.468428611755371,
              -13.951388359069824
            ],
            [
              11.402970314025879,
              -10.71711254119873
            ],
            [
              10.225465774536133,
              -8.154309272766113
            ],
            [
              8.978696823120117,
              -6.180258274078369
            ],
            [
              7.870457172393799,
              -4.760326385498047
            ],
            [
              7.004645347595215,
              -3.7213521003723145
            ],
            [
              6.173465728759766,
              -3.513557195663452
            ],
            [
              4.9959611892700195,
              -3.7559845447540283
            ],
            [
              4.060884475708008,
              -4.725694179534912
            ],
            [
              3.7838246822357178,
              -6.110993385314941
            ],
            [
              4.476474285125732,
              -7.01143741607666
            ],
            [
              5.965671062469482,
              -8.846959114074707
            ],
            [
              7.558764934539795,
              -11.790719985961914
            ],
            [
              8.474621772766113,
              -14.46947956085205
            ],
            [
              9.032204627990723,
              -17.49635887145996
            ],
            [
              9.310996055603027,
              -21.040992736816406
            ],
            [
              9.191514015197754,
              -24.22718048095703
            ],
            [
              8.793240547180176,
              -27.771814346313477
            ]
          ]
        },
        "color": {
          "fill": "#1e88ff",
          "opacity": 0.65
        },
        "outlined": false
      }
    ],
    "viewBox": null
  }
]