[
  {
    "id": "prgl",
    "preop": "orig",
    "shapes": [
      {
        "type": "polygon",
        "geom": {
          "points": [
            [
              -92.79757690429688,
              -44.64492607116699
            ],
            [
              -95.74330139160156,
              -43.93225288391113
            ],
            [
              -97.64376831054688,
              -42.55441093444824
            ],
            [
              -98.83155822753906,
              -41.17657279968262
            ],
            [
              -101.15963745117188,
              -38.80098915100098
            ],
            [
              -102.25240325927734,
              -36.09282112121582
            ],
            [
              -102.25240325927734,
              -33.242116928100586
            ],
            [
              -101.4447021484375,
              -30.248878479003906
            ],
            [
              -99.78179168701172,
              -27.96831703186035
            ],
            [
              -97.97634887695312,
              -26.44794273376465
            ],
            [
              -95.36320495605469,
              -25.307661056518555
            ],
            [
              -92.75006103515625,
              -24.975080490112305
            ],
            [
              -89.47175598144531,
              -25.640243530273438
            ],
            [
              -86.66856384277344,
              -27.730758666992188
            ],
            [
              -84.86312103271484,
              -29.821273803710938
            ],
            [
              -83.01016235351562,
              -32.81451225280762
            ],
            [
              -82.72509002685547,
              -36.33037757873535
            ],
            [
              -83.48527526855469,
              -38.99103355407715
            ],
            [
              -85.24320983886719,
              -41.604177474975586
            ],
            [
              -87.66630554199219,
              -43.55215644836426
            ],
            [
              -90.27944946289062,
              -44.54990577697754
            ]
          ]
        },
        "color": {
          "fill": "#1e88ff",
          "opacity": 0.65
        },
        "outlined": false
      }
    ],
    "viewBox": null
  }
]