[
  {
    "id": "homb",
    "preop": "orig",
    "shapes": [
      {
        "type": "polygon",
        "geom": {
          "points": [
            [
              -92.82081604003906,
              -14.348937034606934
            ],
            [
              -113.01930236816406,
              5.208326816558838
            ],
            [
              -113.17960357666016,
              18.35337257385254
            ],
            [
              -109.332275390625,
              20.43734359741211
            ],
            [
              -105.64524841308594,
              21.23887062072754
            ],
            [
              -105.0040283203125,
              31.177806854248047
            ],
            [
              -102.75975036621094,
              33.26177978515625
            ],
            [
              -72.62232971191406,
              37.75033187866211
            ],
            [
              -65.8895034790039,
              36.78849792480469
            ],
            [
              -54.34750747680664,
              25.086200714111328
            ],
            [
              -54.18720245361328,
              -8.738245964050293
            ],
            [
              -55.62995147705078,
              -9.860384941101074
            ],
            [
              -77.4314956665039,
              -12.906188011169434
            ],
            [
              -77.4314956665039,
              -24.768789291381836
            ],
            [
              -79.83607482910156,
              -25.890928268432617
            ],
            [
              -82.24065399169922,
              -24.608484268188477
            ],
            [
              -82.08035278320312,
              -13.547410011291504
            ],
            [
              -90.5765380859375,
              -14.990158081054688
            ]
          ]
        },
        "color": {
          "fill": "#1e88ff",
          "opacity": 0.35
        },
        "outlined": false
      },
      {
        "type": "polygon",
        "geom": {
          "points": [
            [
              -104.43182373046875,
              54.071197509765625
            ],
            [
              -105.89830780029297,
              54.621131896972656
            ],
            [
              -105.53168487548828,
              55.537681579589844
            ],
            [
              -103.14865112304688,
              55.904300689697266
            ],
            [
              -101.49886322021484,
              55.81264877319336
            ],
            [
              -100.8572769165039,
              54.896095275878906
            ],
            [
              -101.59051513671875,
              54.1628532409668
            ]
          ]
        },
        "color": {
          "fill": "#1e88ff",
          "opacity": 0.65
        },
        "outlined": false
      },
      {
        "type": "polygon",
        "geom": {
          "points": [
            [
              -81.33472442626953,
              57.55409622192383
            ],
            [
              -82.25128173828125,
              58.28733444213867
            ],
            [
              -81.79300689697266,
              59.203887939453125
            ],
            [
              -79.40997314453125,
              59.38719940185547
            ],
            [
              -77.57686614990234,
              58.8372688293457
            ],
            [
              -77.66851806640625,
              58.01237106323242
            ]
          ]
        },
        "color": {
          "fill": "#1e88ff",
          "opacity": 0.65
        },
        "outlined": false
      }
    ],
    "viewBox": "-148.36959838867188 -44.326053619384766 97.63191223144531 147.4810028076172"
  }
]